ramlient/__init__.py
ramlient/core.py
ramlient/errors.py
ramlient/request.py
ramlient/utils.py
ramlient-0.1.4.dist-info/DESCRIPTION.rst
ramlient-0.1.4.dist-info/METADATA
ramlient-0.1.4.dist-info/RECORD
ramlient-0.1.4.dist-info/WHEEL
ramlient-0.1.4.dist-info/metadata.json
ramlient-0.1.4.dist-info/top_level.txt
